magus/__init__.py
magus/configuration.py
magus/main.py
magus/align/__init__.py
magus/align/aligner.py
magus/align/alignment_context.py
magus/align/decompose/__init__.py
magus/align/decompose/decomposer.py
magus/align/decompose/initial_tree.py
magus/align/decompose/kmh.py
magus/align/merge/__init__.py
magus/align/merge/alignment_graph.py
magus/align/merge/alignment_writer.py
magus/align/merge/merger.py
magus/align/merge/optimizer.py
magus/align/merge/graph_build/__init__.py
magus/align/merge/graph_build/graph_builder.py
magus/align/merge/graph_cluster/__init__.py
magus/align/merge/graph_cluster/clean_clusters.py
magus/align/merge/graph_cluster/clusterer.py
magus/align/merge/graph_cluster/mcl.py
magus/align/merge/graph_cluster/mlr_mcl.py
magus/align/merge/graph_cluster/rg.py
magus/align/merge/graph_trace/__init__.py
magus/align/merge/graph_trace/fm.py
magus/align/merge/graph_trace/min_clusters.py
magus/align/merge/graph_trace/mwt_search.py
magus/align/merge/graph_trace/naive.py
magus/align/merge/graph_trace/rg_fast_search.py
magus/align/merge/graph_trace/rg_search.py
magus/align/merge/graph_trace/tracer.py
magus/helpers/__init__.py
magus/helpers/hmmutils.py
magus/helpers/sequenceutils.py
magus/helpers/treeutils.py
magus/tasks/__init__.py
magus/tasks/controller.py
magus/tasks/files.py
magus/tasks/manager.py
magus/tasks/task.py
magus/tools/__init__.py
magus/tools/external_tools.py
magus/tools/clustal/clustalo
magus/tools/fasttree/FastTree
magus/tools/fasttree/FastTreeMP
magus/tools/hmmer/hmmalign
magus/tools/hmmer/hmmbuild
magus/tools/hmmer/hmmsearch
magus/tools/mafft/mafft
magus/tools/mafft/mafftdir/bin/mafft
magus/tools/mafft/mafftdir/libexec/addsingle
magus/tools/mafft/mafftdir/libexec/contrafoldwrap
magus/tools/mafft/mafftdir/libexec/countlen
magus/tools/mafft/mafftdir/libexec/dash_client
magus/tools/mafft/mafftdir/libexec/disttbfast
magus/tools/mafft/mafftdir/libexec/dndblast
magus/tools/mafft/mafftdir/libexec/dndfast7
magus/tools/mafft/mafftdir/libexec/dndpre
magus_msa-0.2.0.dist-info/LICENSE.txt
magus_msa-0.2.0.dist-info/METADATA
magus_msa-0.2.0.dist-info/WHEEL
magus_msa-0.2.0.dist-info/entry_points.txt
magus_msa-0.2.0.dist-info/top_level.txt
magus_msa-0.2.0.dist-info/RECORD
