Metadata-Version: 2.1
Name: magus-msa
Version: 0.2.0
Summary: Multiple Sequence Alignment using Graph Clustering
Author: vlasmirnov
Maintainer: vlasmirnov, Leon Rauschning
License: MIT
Project-URL: homepage, https://github.com/vlasmirnov/MAGUS
Project-URL: issues, https://github.com/vlasmirnov/MAGUS/issues
Classifier: Programming Language :: Python :: 3
Classifier: License :: OSI Approved :: MIT License
Requires-Python: >=3.6
License-File: LICENSE.txt
Requires-Dist: dendropy >=4.5.2
